llsd/__init__.py
llsd/base.py
llsd/fastest_elementtree.py
llsd/serde_binary.py
llsd/serde_notation.py
llsd/serde_xml.py
llsd-1.2.4.dist-info/LICENSE
llsd-1.2.4.dist-info/METADATA
llsd-1.2.4.dist-info/WHEEL
llsd-1.2.4.dist-info/top_level.txt
llsd-1.2.4.dist-info/RECORD
