Metadata-Version: 2.1
Name: llsd
Version: 1.2.4
Summary: Linden Lab Structured Data (LLSD) serialization library
Home-page: https://github.com/secondlife/python-llsd
Author: Linden Research, Inc.
Author-email: opensource-dev@lists.secondlife.com
License: MIT
Platform: UNKNOWN
Classifier: Intended Audience :: Developers
Classifier: License :: OSI Approved :: MIT License
Classifier: Programming Language :: Python :: 2
Classifier: Programming Language :: Python :: 3
Classifier: Topic :: Software Development :: Libraries :: Python Modules
Classifier: Topic :: Software Development
Provides-Extra: dev
Requires-Dist: pytest ; extra == 'dev'
Requires-Dist: pytest-benchmark ; extra == 'dev'
Requires-Dist: pytest-cov (<3) ; extra == 'dev'
